{
  "Catalog/computers-157" : {
    "transaction" : "Catalog/computers-157",
    "sampleCount" : 5,
    "errorCount" : 0,
    "errorPct" : 0.0,
    "meanResTime" : 381.6,
    "medianResTime" : 346.0,
    "minResTime" : 344.0,
    "maxResTime" : 469.0,
    "pct1ResTime" : 469.0,
    "pct2ResTime" : 469.0,
    "pct3ResTime" : 469.0,
    "throughput" : 0.8210180623973727,
    "receivedKBytesPerSec" : 6.061101703612479,
    "sentKBytesPerSec" : 0.6983464183087028
  },
  "Products/apple-icam-72" : {
    "transaction" : "Products/apple-icam-72",
    "sampleCount" : 5,
    "errorCount" : 0,
    "errorPct" : 0.0,
    "meanResTime" : 577.6,
    "medianResTime" : 572.0,
    "minResTime" : 566.0,
    "maxResTime" : 596.0,
    "pct1ResTime" : 596.0,
    "pct2ResTime" : 596.0,
    "pct3ResTime" : 596.0,
    "throughput" : 0.694058856191005,
    "receivedKBytesPerSec" : 9.5217554917407,
    "sentKBytesPerSec" : 0.5727341147279289
  },
  "Home/-4" : {
    "transaction" : "Home/-4",
    "sampleCount" : 5,
    "errorCount" : 0,
    "errorPct" : 0.0,
    "meanResTime" : 1247.2,
    "medianResTime" : 1183.0,
    "minResTime" : 1161.0,
    "maxResTime" : 1533.0,
    "pct1ResTime" : 1533.0,
    "pct2ResTime" : 1533.0,
    "pct3ResTime" : 1533.0,
    "throughput" : 0.5498735290883097,
    "receivedKBytesPerSec" : 5.725558121632025,
    "sentKBytesPerSec" : 0.2448655559221379
  },
  "Catalog/apparel-91" : {
    "transaction" : "Catalog/apparel-91",
    "sampleCount" : 5,
    "errorCount" : 0,
    "errorPct" : 0.0,
    "meanResTime" : 348.8,
    "medianResTime" : 339.0,
    "minResTime" : 330.0,
    "maxResTime" : 387.0,
    "pct1ResTime" : 387.0,
    "pct2ResTime" : 387.0,
    "pct3ResTime" : 387.0,
    "throughput" : 0.7240081088908196,
    "receivedKBytesPerSec" : 5.346771602591949,
    "sentKBytesPerSec" : 0.5847213926295974
  },
  "Catalog/shoes-105" : {
    "transaction" : "Catalog/shoes-105",
    "sampleCount" : 5,
    "errorCount" : 0,
    "errorPct" : 0.0,
    "meanResTime" : 550.0,
    "medianResTime" : 359.0,
    "minResTime" : 345.0,
    "maxResTime" : 1134.0,
    "pct1ResTime" : 1134.0,
    "pct2ResTime" : 1134.0,
    "pct3ResTime" : 1134.0,
    "throughput" : 0.7269555103227683,
    "receivedKBytesPerSec" : 6.786101292163419,
    "sentKBytesPerSec" : 0.5906513521372492
  },
  "Catalog/notebooks-165" : {
    "transaction" : "Catalog/notebooks-165",
    "sampleCount" : 5,
    "errorCount" : 0,
    "errorPct" : 0.0,
    "meanResTime" : 387.4,
    "medianResTime" : 388.0,
    "minResTime" : 360.0,
    "maxResTime" : 430.0,
    "pct1ResTime" : 430.0,
    "pct2ResTime" : 430.0,
    "pct3ResTime" : 430.0,
    "throughput" : 0.8259002312520648,
    "receivedKBytesPerSec" : 7.9625170341922695,
    "sentKBytesPerSec" : 0.6758831970597952
  },
  "Products/build-your-own-computer-16" : {
    "transaction" : "Products/build-your-own-computer-16",
    "sampleCount" : 5,
    "errorCount" : 0,
    "errorPct" : 0.0,
    "meanResTime" : 705.4,
    "medianResTime" : 564.0,
    "minResTime" : 546.0,
    "maxResTime" : 1275.0,
    "pct1ResTime" : 1275.0,
    "pct2ResTime" : 1275.0,
    "pct3ResTime" : 1275.0,
    "throughput" : 0.616827041697508,
    "receivedKBytesPerSec" : 8.449446204971625,
    "sentKBytesPerSec" : 0.4831008666419936
  },
  "Catalog/apple-macbook-pro-13-inch-176" : {
    "transaction" : "Catalog/apple-macbook-pro-13-inch-176",
    "sampleCount" : 5,
    "errorCount" : 0,
    "errorPct" : 0.0,
    "meanResTime" : 602.8,
    "medianResTime" : 572.0,
    "minResTime" : 572.0,
    "maxResTime" : 664.0,
    "pct1ResTime" : 664.0,
    "pct2ResTime" : 664.0,
    "pct3ResTime" : 664.0,
    "throughput" : 0.8069722401549386,
    "receivedKBytesPerSec" : 9.124145113783086,
    "sentKBytesPerSec" : 0.6730022393479664
  },
  "Total" : {
    "transaction" : "Total",
    "sampleCount" : 60,
    "errorCount" : 0,
    "errorPct" : 0.0,
    "meanResTime" : 539.9000000000001,
    "medianResTime" : 396.5,
    "minResTime" : 330.0,
    "maxResTime" : 1533.0,
    "pct1ResTime" : 1158.3,
    "pct2ResTime" : 1194.3999999999999,
    "pct3ResTime" : 1533.0,
    "throughput" : 4.343419719125525,
    "receivedKBytesPerSec" : 44.378099210945415,
    "sentKBytesPerSec" : 3.3264911276603444
  },
  "Products/-59" : {
    "transaction" : "Products/-59",
    "sampleCount" : 5,
    "errorCount" : 0,
    "errorPct" : 0.0,
    "meanResTime" : 363.0,
    "medianResTime" : 355.0,
    "minResTime" : 348.0,
    "maxResTime" : 389.0,
    "pct1ResTime" : 389.0,
    "pct2ResTime" : 389.0,
    "pct3ResTime" : 389.0,
    "throughput" : 0.6963788300835655,
    "receivedKBytesPerSec" : 7.073277550487465,
    "sentKBytesPerSec" : 0.5161636055013927
  },
  "Products/-10" : {
    "transaction" : "Products/-10",
    "sampleCount" : 5,
    "errorCount" : 0,
    "errorPct" : 0.0,
    "meanResTime" : 362.4,
    "medianResTime" : 364.0,
    "minResTime" : 353.0,
    "maxResTime" : 373.0,
    "pct1ResTime" : 373.0,
    "pct2ResTime" : 373.0,
    "pct3ResTime" : 373.0,
    "throughput" : 0.6310740880979427,
    "receivedKBytesPerSec" : 6.411441570427868,
    "sentKBytesPerSec" : 0.44865423450713116
  },
  "Catalog/-83" : {
    "transaction" : "Catalog/-83",
    "sampleCount" : 5,
    "errorCount" : 0,
    "errorPct" : 0.0,
    "meanResTime" : 360.8,
    "medianResTime" : 362.0,
    "minResTime" : 344.0,
    "maxResTime" : 377.0,
    "pct1ResTime" : 377.0,
    "pct2ResTime" : 377.0,
    "pct3ResTime" : 377.0,
    "throughput" : 0.719320961012804,
    "receivedKBytesPerSec" : 7.305182033160697,
    "sentKBytesPerSec" : 0.540193182635592
  },
  "Products/25-virtual-gift-card-63" : {
    "transaction" : "Products/25-virtual-gift-card-63",
    "sampleCount" : 5,
    "errorCount" : 0,
    "errorPct" : 0.0,
    "meanResTime" : 591.8,
    "medianResTime" : 558.0,
    "minResTime" : 553.0,
    "maxResTime" : 731.0,
    "pct1ResTime" : 731.0,
    "pct2ResTime" : 731.0,
    "pct3ResTime" : 731.0,
    "throughput" : 0.678886625933469,
    "receivedKBytesPerSec" : 6.28354654616429,
    "sentKBytesPerSec" : 0.5502694331296674
  }
}